MANIFEST.in
README.rst
requirements.txt
setup.cfg
setup.py
xena_rest_server.py
xenavalkyrie_rest/__init__.py
xenavalkyrie_rest/logging_dicts.py
xenavalkyrie_rest/settings.py
xenavalkyrie_rest/wsgi.py
xenavalkyrie_rest.egg-info/PKG-INFO
xenavalkyrie_rest.egg-info/SOURCES.txt
xenavalkyrie_rest.egg-info/dependency_links.txt
xenavalkyrie_rest.egg-info/requires.txt
xenavalkyrie_rest.egg-info/top_level.txt
xenavalkyrie_rest/namespaces/__init__.py
xenavalkyrie_rest/namespaces/base_ns.py
xenavalkyrie_rest/namespaces/capture_ns.py
xenavalkyrie_rest/namespaces/chassis_ns.py
xenavalkyrie_rest/namespaces/modifier_ns.py
xenavalkyrie_rest/namespaces/module_ns.py
xenavalkyrie_rest/namespaces/port_ns.py
xenavalkyrie_rest/namespaces/serializers.py
xenavalkyrie_rest/namespaces/server_ns.py
xenavalkyrie_rest/namespaces/session_ns.py
xenavalkyrie_rest/namespaces/stream_ns.py
xenavalkyrie_rest/test/__init__.py
xenavalkyrie_rest/test/test_base.py
xenavalkyrie_rest/test/test_offline.py
xenavalkyrie_rest/test/test_online.py