Metadata-Version: 1.1
Name: xenavalkyrie-rest
Version: 0.6.2
Summary: Stand-alone REST API server to manage Xena Valkyrie chassis
Home-page: https://github.com/xenadevel/RestXenaValkyrie/
Author: Yoram Shamir
Author-email: yoram@ignissoft.com
License: Apache Software License
Platform: any
Classifier: Programming Language :: Python
Classifier: Development Status :: 4 - Beta
Classifier: Natural Language :: English
Classifier: Intended Audience :: Developers
Classifier: License :: OSI Approved :: Apache Software License
Classifier: Operating System :: OS Independent
Classifier: Topic :: Software Development :: Testing :: Traffic Generation
Classifier: Programming Language :: Python :: 2.7
Classifier: Programming Language :: Python :: 3.6
